linear/Exceptions.py
linear/Linear.py
linear/__init__.py
linear_py-0.0.6.dist-info/LICENSE
linear_py-0.0.6.dist-info/METADATA
linear_py-0.0.6.dist-info/WHEEL
linear_py-0.0.6.dist-info/top_level.txt
linear_py-0.0.6.dist-info/RECORD
